pyFileFinder/__init__.py
pyFileFinder/finder.py
tests/__init__.py
tests/unit/__init__.py
tests/unit/test_finder.py
pyFileFinder-0.8.dist-info/LICENSE
pyFileFinder-0.8.dist-info/METADATA
pyFileFinder-0.8.dist-info/WHEEL
pyFileFinder-0.8.dist-info/top_level.txt
pyFileFinder-0.8.dist-info/RECORD
