Metadata-Version: 2.1
Name: pyFileFinder
Version: 0.8
Summary: module to easily find files in system, zip archives or ftp servers using regex
Home-page: https://github.com/20centcroak/pyFileFinder
Author: 20centCroak
Author-email: 
License: UNKNOWN
Platform: UNKNOWN
Classifier: Programming Language :: Python :: 3
Classifier: License :: OSI Approved :: MIT License
Classifier: Operating System :: OS Independent
Requires-Python: >=3.6
